[{"year":1920,"value":2028},{"year":1921,"value":2203},{"year":1922,"value":2058},{"year":1923,"value":2240},{"year":1924,"value":2397},{"year":1925,"value":2327},{"year":1926,"value":2327},{"year":1927,"value":2453},{"year":1928,"value":2482},{"year":1929,"value":2742},{"year":1930,"value":2831},{"year":1931,"value":2582},{"year":1932,"value":2200},{"year":1933,"value":2165},{"year":1934,"value":2410},{"year":1935,"value":2729},{"year":1936,"value":3674},{"year":1937,"value":3516},{"year":1938,"value":3545},{"year":1939,"value":3916},{"year":1940,"value":4371},{"year":1941,"value":4503},{"year":1942,"value":4463},{"year":1943,"value":2925},{"year":1944,"value":2775},{"year":1945,"value":2761},{"year":1946,"value":3191},{"year":1947,"value":3148},{"year":1948,"value":3169},{"year":1949,"value":3365},{"year":1950,"value":3323},{"year":1951,"value":3263},{"year":1952,"value":3226},{"year":1953,"value":3239},{"year":1954,"value":3194},{"year":1955,"value":3170},{"year":1956,"value":3347},{"year":1957,"value":3424},{"year":1958,"value":3470},{"year":1959,"value":3524},{"year":1960,"value":3496},{"year":1961,"value":3532},{"year":1962,"value":3543},{"year":1963,"value":3762},{"year":1964,"value":3814},{"year":1965,"value":3900},{"year":1966,"value":4033},{"year":1967,"value":4114},{"year":1968,"value":4385},{"year":1969,"value":4497},{"year":1970,"value":4653},{"year":1971,"value":4801},{"year":1972,"value":5037},{"year":1973,"value":5255},{"year":1974,"value":5461},{"year":1975,"value":5439},{"year":1976,"value":5705},{"year":1977,"value":6005},{"year":1978,"value":6156},{"year":1979,"value":6298},{"year":1980,"value":6384},{"year":1981,"value":6256},{"year":1982,"value":5903},{"year":1983,"value":5585},{"year":1984,"value":5469},{"year":1985,"value":5292},{"year":1986,"value":5136},{"year":1987,"value":5098},{"year":1988,"value":5086},{"year":1989,"value":5144},{"year":1990,"value":5165},{"year":1991,"value":5166.5499},{"year":1992,"value":5303.5985},{"year":1993,"value":5382.9787},{"year":1994,"value":5414.5412},{"year":1995,"value":5501.0422},{"year":1996,"value":5511.9047},{"year":1997,"value":5601.2075},{"year":1998,"value":5730.6458},{"year":1999,"value":5824.8833},{"year":2000,"value":5860.2719},{"year":2001,"value":5882.7197},{"year":2002,"value":5980.242},{"year":2003,"value":6004.1447},{"year":2004,"value":6070.1942},{"year":2005,"value":6130.4823},{"year":2006,"value":6305.8186},{"year":2007,"value":6545.7524},{"year":2008,"value":6604.6824},{"year":2009,"value":6488.6462},{"year":2010,"value":6526.4576},{"year":2011,"value":6650},{"year":2012,"value":6714},{"year":2013,"value":6829},{"year":2014,"value":6981},{"year":2015,"value":7138},{"year":2016,"value":7221}]
