[{"year":1870,"value":167.99},{"year":1871},{"year":1872},{"year":1873},{"year":1874},{"year":1875},{"year":1876},{"year":1877},{"year":1878},{"year":1879},{"year":1880,"value":169.865},{"year":1881},{"year":1882},{"year":1883},{"year":1884},{"year":1885},{"year":1886},{"year":1887},{"year":1888},{"year":1889},{"year":1890,"value":169.836},{"year":1891},{"year":1892},{"year":1893},{"year":1894},{"year":1895},{"year":1896},{"year":1897},{"year":1898},{"year":1899},{"year":1900,"value":167.854},{"year":1901},{"year":1902},{"year":1903},{"year":1904},{"year":1905},{"year":1906},{"year":1907},{"year":1908},{"year":1909},{"year":1910,"value":169},{"year":1911},{"year":1912},{"year":1913},{"year":1914},{"year":1915},{"year":1916},{"year":1917},{"year":1918},{"year":1919},{"year":1920,"value":170.985},{"year":1921},{"year":1922},{"year":1923},{"year":1924},{"year":1925},{"year":1926},{"year":1927},{"year":1928},{"year":1929},{"year":1930,"value":167.9}]
